jupyter_pyfilesystem/__init__.py
jupyter_pyfilesystem/contents.py
tests/__init__.py
tests/test_pyfilesystem.py
tests/todo-test_hybrid_manager.py
tests/utils.py
jupyter_pyfilesystem-0.0.5.dist-info/LICENSE
jupyter_pyfilesystem-0.0.5.dist-info/METADATA
jupyter_pyfilesystem-0.0.5.dist-info/WHEEL
jupyter_pyfilesystem-0.0.5.dist-info/top_level.txt
jupyter_pyfilesystem-0.0.5.dist-info/RECORD
