Metadata-Version: 2.1
Name: jupyter-pyfilesystem
Version: 0.0.5
Summary: Jupyter Notebook PyFilesystem Contents Manager
Home-page: https://github.com/manics/jupyter-pyfilesystem
Author: Simon Li
License: MIT
Platform: UNKNOWN
Classifier: Framework :: Jupyter
Classifier: License :: OSI Approved :: MIT License
Classifier: Operating System :: OS Independent
Classifier: Programming Language :: Python
Classifier: Programming Language :: Python :: 3
Classifier: Topic :: Scientific/Engineering
Classifier: Topic :: System :: Filesystems
Requires-Python: >=3.5
Requires-Dist: notebook
Requires-Dist: fs (<3,>=2)
